cmdbomb/__init__.py
cmdbomb/cmd.py
cmdbomb/helper.py
cmdbomb-0.0.2.dist-info/LICENSE
cmdbomb-0.0.2.dist-info/METADATA
cmdbomb-0.0.2.dist-info/WHEEL
cmdbomb-0.0.2.dist-info/top_level.txt
cmdbomb-0.0.2.dist-info/RECORD
